{
  "championDetail" : {
    "blurb" : "All who know the name Medarda respect and fear the family's leader, Ambessa. As a Noxian general, she embodies a deadly combination of ruthless strength and fearless resolve in battle. Her role as matriarch is no different, requiring great cunning to...",
    "id" : "Ambessa",
    "image" : {
      "full" : "Ambessa.png",
      "group" : "champion",
      "h" : 48,
      "sprite" : "champion0.png",
      "w" : 48,
      "x" : 240,
      "y" : 0
    },
    "info" : {
      "attack" : 9,
      "defense" : 2,
      "difficulty" : 10,
      "magic" : 0
    },
    "key" : "799",
    "name" : "Ambessa",
    "passive" : {
      "description" : "Entering an attack or movement command while casting an ability will cause Ambessa to dash a short distance once the ability is cast, granting her next attack bonus range, damage, and attack speed, and refunding energy.",
      "image" : {
        "full" : "Icon_Ambessa_Passive.Domina.png",
        "group" : "passive",
        "h" : 48,
        "sprite" : "passive0.png",
        "w" : 48,
        "x" : 240,
        "y" : 0
      },
      "name" : "Drakehound's Step"
    },
    "spells" : [
      {
        "description" : "Ambessa sweeps her twin drakehounds in a semicircle in front of her, dealing bonus damage to enemies hit by the blades. Striking an enemy will transform the next cast of this ability for a short period of time, causing her to slam her twin drakehounds down in a line in front of her, dealing bonus damage to the first enemy hit.",
        "id" : "AmbessaQ",
        "image" : {
          "full" : "AmbessaQ.png",
          "group" : "spell",
          "h" : 48,
          "sprite" : "spell0.png",
          "w" : 48,
          "x" : 384,
          "y" : 144
        },
        "name" : "Cunning Sweep \/ Sundering Slam"
      },
      {
        "description" : "Ambessa gains a shield, briefly braces herself, and then slams the ground to damage nearby enemies. If she blocked any non-minion damage while bracing herself, this ability will deal increased damage.",
        "id" : "AmbessaW",
        "image" : {
          "full" : "AmbessaW.png",
          "group" : "spell",
          "h" : 48,
          "sprite" : "spell0.png",
          "w" : 48,
          "x" : 432,
          "y" : 144
        },
        "name" : "Repudiation"
      },
      {
        "description" : "Ambessa whips her twin drakehounds around herself, damaging and slowing nearby enemies. Initiating Drakehound's Step from this ability causes her to strike a second time at the end of its dash.",
        "id" : "AmbessaE",
        "image" : {
          "full" : "AmbessaE.png",
          "group" : "spell",
          "h" : 48,
          "sprite" : "spell1.png",
          "w" : 48,
          "x" : 0,
          "y" : 0
        },
        "name" : "Lacerate"
      },
      {
        "description" : "Ambessa blinks to the farthest enemy champion in a line of her choosing and suppresses them upon her arrival. She then slams the enemy into the ground where they take damage and are stunned.",
        "id" : "AmbessaR",
        "image" : {
          "full" : "AmbessaR.png",
          "group" : "spell",
          "h" : 48,
          "sprite" : "spell1.png",
          "w" : 48,
          "x" : 48,
          "y" : 0
        },
        "name" : "Public Execution"
      }
    ],
    "title" : "Matriarch of War"
  },
  "championName" : "Ambessa",
  "fullRunePageFrequency" : [
    {
      "primaryPerks" : {
        "perk1" : 8010,
        "perk2" : 9111,
        "perk3" : 9105,
        "perk4" : 8299
      },
      "primaryStyle" : 8000,
      "subPerks" : {
        "perk1" : 8451,
        "perk2" : 8444
      },
      "subStyle" : 8400
    },
    1,
    {
      "primaryPerks" : {
        "perk1" : 8437,
        "perk2" : 8401,
        "perk3" : 8444,
        "perk4" : 8242
      },
      "primaryStyle" : 8400,
      "subPerks" : {
        "perk1" : 8304,
        "perk2" : 8345
      },
      "subStyle" : 8300
    },
    3,
    {
      "primaryPerks" : {
        "perk1" : 8437,
        "perk2" : 8401,
        "perk3" : 8444,
        "perk4" : 8451
      },
      "primaryStyle" : 8400,
      "subPerks" : {
        "perk1" : 8304,
        "perk2" : 8345
      },
      "subStyle" : 8300
    },
    1,
    {
      "primaryPerks" : {
        "perk1" : 8112,
        "perk2" : 8143,
        "perk3" : 8141,
        "perk4" : 8106
      },
      "primaryStyle" : 8100,
      "subPerks" : {
        "perk1" : 8401,
        "perk2" : 8444
      },
      "subStyle" : 8400
    },
    1,
    {
      "primaryPerks" : {
        "perk1" : 8112,
        "perk2" : 8143,
        "perk3" : 8140,
        "perk4" : 8106
      },
      "primaryStyle" : 8100,
      "subPerks" : {
        "perk1" : 8401,
        "perk2" : 8473
      },
      "subStyle" : 8400
    },
    1,
    {
      "primaryPerks" : {
        "perk1" : 8437,
        "perk2" : 8401,
        "perk3" : 8444,
        "perk4" : 8451
      },
      "primaryStyle" : 8400,
      "subPerks" : {
        "perk1" : 8345,
        "perk2" : 8304
      },
      "subStyle" : 8300
    },
    1,
    {
      "primaryPerks" : {
        "perk1" : 8437,
        "perk2" : 8401,
        "perk3" : 8473,
        "perk4" : 8451
      },
      "primaryStyle" : 8400,
      "subPerks" : {
        "perk1" : 8345,
        "perk2" : 8304
      },
      "subStyle" : 8300
    },
    1,
    {
      "primaryPerks" : {
        "perk1" : 8437,
        "perk2" : 8401,
        "perk3" : 8444,
        "perk4" : 8242
      },
      "primaryStyle" : 8400,
      "subPerks" : {
        "perk1" : 8345,
        "perk2" : 8347
      },
      "subStyle" : 8300
    },
    1,
    {
      "primaryPerks" : {
        "perk1" : 8112,
        "perk2" : 8143,
        "perk3" : 8140,
        "perk4" : 8106
      },
      "primaryStyle" : 8100,
      "subPerks" : {
        "perk1" : 8401,
        "perk2" : 8444
      },
      "subStyle" : 8400
    },
    2
  ],
  "id" : "Ambessa",
  "items" : {
    "allItems" : {
      "1028" : 2,
      "1033" : 2,
      "1036" : 4,
      "1054" : 6,
      "1055" : 1,
      "2031" : 1,
      "2055" : 2,
      "2422" : 1,
      "3033" : 1,
      "3035" : 1,
      "3047" : 6,
      "3071" : 3,
      "3111" : 2,
      "3123" : 1,
      "3133" : 1,
      "3134" : 2,
      "3142" : 1,
      "3155" : 2,
      "3161" : 3,
      "3171" : 1,
      "3173" : 1,
      "3174" : 1,
      "3340" : 7,
      "3363" : 1,
      "3364" : 4,
      "3814" : 2,
      "6333" : 4,
      "6610" : 1,
      "6692" : 10,
      "6694" : 1,
      "6695" : 1,
      "6699" : 4
    },
    "boots" : {
      "3047" : 7,
      "3111" : 3,
      "3158" : 1
    },
    "fifthCore" : {

    },
    "firstCore" : {
      "6692" : 10,
      "6699" : 2
    },
    "fourthCore" : {

    },
    "secondCore" : {
      "3033" : 1,
      "3071" : 2,
      "3142" : 1,
      "3161" : 2,
      "3814" : 1,
      "6333" : 1,
      "6610" : 1,
      "6699" : 2
    },
    "sixthCore" : {

    },
    "starters" : [
      [
        2003,
        1055
      ],
      1,
      [
        2003,
        1054
      ],
      11
    ],
    "thirdCore" : {
      "3071" : 1,
      "3161" : 1,
      "3814" : 1,
      "6333" : 3,
      "6694" : 1,
      "6695" : 1
    }
  },
  "spellFrequency" : [
    [
      "SummonerTeleport.png",
      "SummonerFlash.png"
    ],
    12
  ],
  "totalGames" : 12,
  "totalWins" : 6,
  "version" : "15.18.1"
}