{
  "championDetail" : {
    "blurb" : "Raised in one of Demacia's lesser quarters, Sylas of Dregbourne has come to symbolize the darker side of the Great City. As a boy, his ability to root out hidden sorcery caught the attention of the notorious mageseekers, who eventually imprisoned him...",
    "id" : "Sylas",
    "image" : {
      "full" : "Sylas.png",
      "group" : "champion",
      "h" : 48,
      "sprite" : "champion4.png",
      "w" : 48,
      "x" : 0,
      "y" : 48
    },
    "info" : {
      "attack" : 3,
      "defense" : 4,
      "difficulty" : 5,
      "magic" : 8
    },
    "key" : "517",
    "name" : "Sylas",
    "passive" : {
      "description" : "After casting a spell, Sylas stores a charge of Petricite Burst. Sylas's basic attacks will expend a charge and whirl his energized chains around him dealing bonus magic damage to enemies hit. While Sylas has a charge of Petricite Burst, he gains attack speed. ",
      "image" : {
        "full" : "SylasP.png",
        "group" : "passive",
        "h" : 48,
        "sprite" : "passive4.png",
        "w" : 48,
        "x" : 0,
        "y" : 48
      },
      "name" : "Petricite Burst"
    },
    "spells" : [
      {
        "description" : "Sylas lashes his chains out, intersecting at his targeted location dealing damage to and slowing enemies. <br><br>After a delay, magical energy explodes from the intersection point dealing damage.",
        "id" : "SylasQ",
        "image" : {
          "full" : "SylasQ.png",
          "group" : "spell",
          "h" : 48,
          "sprite" : "spell13.png",
          "w" : 48,
          "x" : 384,
          "y" : 48
        },
        "name" : "Chain Lash"
      },
      {
        "description" : "Sylas lunges at an enemy with magical force dealing damage and healing himself against enemy champions.",
        "id" : "SylasW",
        "image" : {
          "full" : "SylasW.png",
          "group" : "spell",
          "h" : 48,
          "sprite" : "spell13.png",
          "w" : 48,
          "x" : 432,
          "y" : 48
        },
        "name" : "Kingslayer"
      },
      {
        "description" : "Sylas dashes to a location. Sylas can recast the ability to throw his chains out, pulling himself to an enemy he hits.",
        "id" : "SylasE",
        "image" : {
          "full" : "SylasE.png",
          "group" : "spell",
          "h" : 48,
          "sprite" : "spell13.png",
          "w" : 48,
          "x" : 0,
          "y" : 96
        },
        "name" : "Abscond \/ Abduct"
      },
      {
        "description" : "Sylas steals the enemy's ultimate ability and can cast it freely.",
        "id" : "SylasR",
        "image" : {
          "full" : "SylasR.png",
          "group" : "spell",
          "h" : 48,
          "sprite" : "spell13.png",
          "w" : 48,
          "x" : 48,
          "y" : 96
        },
        "name" : "Hijack"
      }
    ],
    "title" : "the Unshackled"
  },
  "championName" : "Sylas",
  "fullRunePageFrequency" : [
    {
      "primaryPerks" : {
        "perk1" : 8010,
        "perk2" : 8009,
        "perk3" : 9105,
        "perk4" : 8299
      },
      "primaryStyle" : 8000,
      "subPerks" : {
        "perk1" : 8444,
        "perk2" : 8451
      },
      "subStyle" : 8400
    },
    1,
    {
      "primaryPerks" : {
        "perk1" : 8010,
        "perk2" : 9111,
        "perk3" : 9105,
        "perk4" : 8017
      },
      "primaryStyle" : 8000,
      "subPerks" : {
        "perk1" : 8347,
        "perk2" : 8304
      },
      "subStyle" : 8300
    },
    1,
    {
      "primaryPerks" : {
        "perk1" : 8128,
        "perk2" : 8143,
        "perk3" : 8140,
        "perk4" : 8135
      },
      "primaryStyle" : 8100,
      "subPerks" : {
        "perk1" : 9105,
        "perk2" : 8299
      },
      "subStyle" : 8000
    },
    1,
    {
      "primaryPerks" : {
        "perk1" : 8010,
        "perk2" : 9111,
        "perk3" : 9105,
        "perk4" : 8299
      },
      "primaryStyle" : 8000,
      "subPerks" : {
        "perk1" : 8304,
        "perk2" : 8347
      },
      "subStyle" : 8300
    },
    5,
    {
      "primaryPerks" : {
        "perk1" : 8112,
        "perk2" : 8143,
        "perk3" : 8140,
        "perk4" : 8105
      },
      "primaryStyle" : 8100,
      "subPerks" : {
        "perk1" : 8345,
        "perk2" : 8347
      },
      "subStyle" : 8300
    },
    1,
    {
      "primaryPerks" : {
        "perk1" : 8128,
        "perk2" : 8143,
        "perk3" : 8140,
        "perk4" : 8135
      },
      "primaryStyle" : 8100,
      "subPerks" : {
        "perk1" : 8347,
        "perk2" : 8304
      },
      "subStyle" : 8300
    },
    1,
    {
      "primaryPerks" : {
        "perk1" : 8112,
        "perk2" : 8143,
        "perk3" : 8140,
        "perk4" : 8105
      },
      "primaryStyle" : 8100,
      "subPerks" : {
        "perk1" : 8444,
        "perk2" : 8451
      },
      "subStyle" : 8400
    },
    2,
    {
      "primaryPerks" : {
        "perk1" : 8128,
        "perk2" : 8143,
        "perk3" : 8137,
        "perk4" : 8135
      },
      "primaryStyle" : 8100,
      "subPerks" : {
        "perk1" : 8304,
        "perk2" : 8347
      },
      "subStyle" : 8300
    },
    1,
    {
      "primaryPerks" : {
        "perk1" : 8010,
        "perk2" : 8009,
        "perk3" : 9105,
        "perk4" : 8299
      },
      "primaryStyle" : 8000,
      "subPerks" : {
        "perk1" : 8444,
        "perk2" : 8242
      },
      "subStyle" : 8400
    },
    1,
    {
      "primaryPerks" : {
        "perk1" : 8010,
        "perk2" : 9111,
        "perk3" : 9105,
        "perk4" : 8299
      },
      "primaryStyle" : 8000,
      "subPerks" : {
        "perk1" : 8304,
        "perk2" : 8316
      },
      "subStyle" : 8300
    },
    1,
    {
      "primaryPerks" : {
        "perk1" : 8112,
        "perk2" : 8143,
        "perk3" : 8140,
        "perk4" : 8105
      },
      "primaryStyle" : 8100,
      "subPerks" : {
        "perk1" : 8237,
        "perk2" : 8210
      },
      "subStyle" : 8200
    },
    1,
    {
      "primaryPerks" : {
        "perk1" : 8128,
        "perk2" : 8143,
        "perk3" : 8140,
        "perk4" : 8135
      },
      "primaryStyle" : 8100,
      "subPerks" : {
        "perk1" : 8304,
        "perk2" : 8347
      },
      "subStyle" : 8300
    },
    2,
    {
      "primaryPerks" : {
        "perk1" : 8128,
        "perk2" : 8143,
        "perk3" : 8137,
        "perk4" : 8135
      },
      "primaryStyle" : 8100,
      "subPerks" : {
        "perk1" : 9105,
        "perk2" : 9111
      },
      "subStyle" : 8000
    },
    1
  ],
  "id" : "Sylas",
  "items" : {
    "allItems" : {
      "1052" : 4,
      "1056" : 3,
      "1058" : 2,
      "1082" : 12,
      "1101" : 1,
      "2055" : 1,
      "2420" : 1,
      "2421" : 1,
      "3020" : 9,
      "3041" : 2,
      "3089" : 3,
      "3100" : 5,
      "3102" : 2,
      "3111" : 2,
      "3145" : 1,
      "3147" : 1,
      "3152" : 13,
      "3157" : 12,
      "3158" : 2,
      "3161" : 1,
      "3175" : 5,
      "3340" : 2,
      "3363" : 3,
      "3364" : 14,
      "4629" : 1,
      "4633" : 3,
      "4645" : 7,
      "6333" : 1,
      "6657" : 1,
      "6692" : 1,
      "8010" : 3
    },
    "boots" : {
      "3020" : 14,
      "3111" : 2,
      "3158" : 3
    },
    "fifthCore" : {
      "3102" : 1,
      "3157" : 1
    },
    "firstCore" : {
      "3100" : 3,
      "3152" : 14,
      "6657" : 1,
      "6692" : 1
    },
    "fourthCore" : {
      "3041" : 1,
      "3089" : 2,
      "3157" : 3,
      "6333" : 1,
      "8010" : 1
    },
    "secondCore" : {
      "3041" : 1,
      "3100" : 1,
      "3157" : 1,
      "4629" : 1,
      "4633" : 3,
      "4645" : 7,
      "8010" : 2
    },
    "sixthCore" : {

    },
    "starters" : [
      [
        2003,
        1056
      ],
      5,
      [
        1102
      ],
      1,
      [
        1101
      ],
      1,
      [
        2031,
        1082
      ],
      1,
      [
        1101,
        2003
      ],
      5,
      [
        1102,
        2003
      ],
      6
    ],
    "thirdCore" : {
      "3041" : 1,
      "3089" : 1,
      "3102" : 1,
      "3157" : 7,
      "3161" : 1,
      "4633" : 1
    }
  },
  "spellFrequency" : [
    [
      "SummonerSmite.png",
      "SummonerFlash.png"
    ],
    13,
    [
      "SummonerFlash.png",
      "SummonerDot.png"
    ],
    2,
    [
      "SummonerTeleport.png",
      "SummonerFlash.png"
    ],
    4
  ],
  "totalGames" : 19,
  "totalWins" : 10,
  "version" : "15.18.1"
}