{
  "championName" : "Xayah",
  "fullRunePageFrequency" : [
    {
      "primaryPerks" : {
        "perk1" : 8008,
        "perk2" : 8009,
        "perk3" : 9103,
        "perk4" : 8017
      },
      "primaryStyle" : 8000,
      "subPerks" : {
        "perk1" : 8347,
        "perk2" : 8304
      },
      "subStyle" : 8300
    },
    1,
    {
      "primaryPerks" : {
        "perk1" : 8010,
        "perk2" : 9111,
        "perk3" : 9104,
        "perk4" : 8017
      },
      "primaryStyle" : 8000,
      "subPerks" : {
        "perk1" : 8304,
        "perk2" : 8347
      },
      "subStyle" : 8300
    },
    1,
    {
      "primaryPerks" : {
        "perk1" : 8008,
        "perk2" : 8009,
        "perk3" : 9103,
        "perk4" : 8017
      },
      "primaryStyle" : 8000,
      "subPerks" : {
        "perk1" : 8304,
        "perk2" : 8345
      },
      "subStyle" : 8300
    },
    1
  ],
  "items" : {
    "allItems" : {
      "1018" : 1,
      "1042" : 1,
      "1055" : 2,
      "1083" : 2,
      "3006" : 2,
      "3031" : 2,
      "3032" : 1,
      "3036" : 2,
      "3072" : 1,
      "3172" : 1,
      "3340" : 1,
      "3363" : 2,
      "3508" : 2,
      "6675" : 1
    },
    "boots" : {
      "3006" : 3
    },
    "fifthCore" : {

    },
    "firstCore" : {
      "3032" : 1,
      "3508" : 2
    },
    "fourthCore" : {
      "3072" : 1
    },
    "secondCore" : {
      "3031" : 1,
      "6675" : 1
    },
    "sixthCore" : {

    },
    "starters" : [
      [
        1055,
        2003
      ],
      3
    ],
    "thirdCore" : {
      "3031" : 1,
      "3036" : 1
    }
  },
  "spellFrequency" : [
    [
      "SummonerHaste.png",
      "SummonerFlash.png"
    ],
    1,
    [
      "SummonerFlash.png",
      "SummonerBarrier.png"
    ],
    2
  ],
  "totalGames" : 3,
  "totalWins" : 3
}